mimo_cli/__init__.py
mimo_cli/agent.py
mimo_cli/cli.py
mimo_cli/config.py
mimo_cli/llm.py
mimo_cli/permissions.py
mimo_cli/tools/__init__.py
mimo_cli/tools/bash.py
mimo_cli/tools/editor.py
mimo_cli/types.py
mimo_cli/ui.py
mimo_cli-0.1.0.dist-info/WHEEL
mimo_cli-0.1.0.dist-info/entry_points.txt
mimo_cli-0.1.0.dist-info/METADATA
mimo_cli-0.1.0.dist-info/RECORD
