Metadata-Version: 2.3
Name: mimo-cli
Version: 0.1.0
Summary: A general assistant that appears in your terminal
Author: Linghao Zhang
Author-email: Linghao Zhang <zhanglinghao@xiaomi.com>
Requires-Dist: litellm>=1.0.0
Requires-Dist: rich>=13.0.0
Requires-Dist: click>=8.0.0
Requires-Dist: prompt-toolkit>=3.0.0
Requires-Python: >=3.12
